{
  "parent": "minecraft:recipes/root",
  "rewards": {
    "recipes": [
      "mekanism:processing/copper/slurry/dirty"
    ]
  },
  "criteria": {
    "has_chemical_dissolution_chamber": {
      "trigger": "minecraft:inventory_changed",
      "conditions": {
        "items": [
          {
            "item": "mekanism:chemical_dissolution_chamber"
          }
        ]
      }
    },
    "has_copper_ore": {
      "trigger": "minecraft:inventory_changed",
      "conditions": {
        "items": [
          {
            "tag": "forge:ores/copper"
          }
        ]
      }
    },
    "has_the_recipe": {
      "trigger": "minecraft:recipe_unlocked",
      "conditions": {
        "recipe": "mekanism:processing/copper/slurry/dirty"
      }
    }
  },
  "requirements": [
    [
      "has_chemical_dissolution_chamber",
      "has_copper_ore",
      "has_the_recipe"
    ]
  ]
}