{
  "parent": "minecraft:recipes/root",
  "rewards": {
    "recipes": [
      "mekanismtools:bronze/nugget_from_blasting"
    ]
  },
  "criteria": {
    "has_bronze_helmet": {
      "trigger": "minecraft:inventory_changed",
      "conditions": {
        "items": [
          {
            "item": "mekanismtools:bronze_helmet"
          }
        ]
      }
    },
    "has_bronze_chestplate": {
      "trigger": "minecraft:inventory_changed",
      "conditions": {
        "items": [
          {
            "item": "mekanismtools:bronze_chestplate"
          }
        ]
      }
    },
    "has_bronze_leggings": {
      "trigger": "minecraft:inventory_changed",
      "conditions": {
        "items": [
          {
            "item": "mekanismtools:bronze_leggings"
          }
        ]
      }
    },
    "has_bronze_boots": {
      "trigger": "minecraft:inventory_changed",
      "conditions": {
        "items": [
          {
            "item": "mekanismtools:bronze_boots"
          }
        ]
      }
    },
    "has_bronze_sword": {
      "trigger": "minecraft:inventory_changed",
      "conditions": {
        "items": [
          {
            "item": "mekanismtools:bronze_sword"
          }
        ]
      }
    },
    "has_bronze_axe": {
      "trigger": "minecraft:inventory_changed",
      "conditions": {
        "items": [
          {
            "item": "mekanismtools:bronze_axe"
          }
        ]
      }
    },
    "has_bronze_pickaxe": {
      "trigger": "minecraft:inventory_changed",
      "conditions": {
        "items": [
          {
            "item": "mekanismtools:bronze_pickaxe"
          }
        ]
      }
    },
    "has_bronze_shovel": {
      "trigger": "minecraft:inventory_changed",
      "conditions": {
        "items": [
          {
            "item": "mekanismtools:bronze_shovel"
          }
        ]
      }
    },
    "has_bronze_hoe": {
      "trigger": "minecraft:inventory_changed",
      "conditions": {
        "items": [
          {
            "item": "mekanismtools:bronze_hoe"
          }
        ]
      }
    },
    "has_bronze_paxel": {
      "trigger": "minecraft:inventory_changed",
      "conditions": {
        "items": [
          {
            "item": "mekanismtools:bronze_paxel"
          }
        ]
      }
    },
    "has_the_recipe": {
      "trigger": "minecraft:recipe_unlocked",
      "conditions": {
        "recipe": "mekanismtools:bronze/nugget_from_blasting"
      }
    }
  },
  "requirements": [
    [
      "has_bronze_helmet",
      "has_bronze_chestplate",
      "has_bronze_leggings",
      "has_bronze_boots",
      "has_bronze_sword",
      "has_bronze_axe",
      "has_bronze_pickaxe",
      "has_bronze_shovel",
      "has_bronze_hoe",
      "has_bronze_paxel",
      "has_the_recipe"
    ]
  ]
}