{
  "parent": "minecraft:recipes/root",
  "rewards": {
    "recipes": [
      "mekanism:free_runners"
    ]
  },
  "criteria": {
    "has_energy_tablet": {
      "trigger": "minecraft:inventory_changed",
      "conditions": {
        "items": [
          {
            "item": "mekanism:energy_tablet"
          }
        ]
      }
    },
    "has_the_recipe": {
      "trigger": "minecraft:recipe_unlocked",
      "conditions": {
        "recipe": "mekanism:free_runners"
      }
    }
  },
  "requirements": [
    [
      "has_energy_tablet",
      "has_the_recipe"
    ]
  ]
}