{
  "type": "mekanism:sawing",
  "conditions": [
    {
      "type": "forge:and",
      "values": [
        {
          "type": "mekanism:mod_version_loaded",
          "minVersion": "1.20.1-11.0.1.0",
          "modid": "ilikewood"
        },
        {
          "type": "mekanism:condition_exists",
          "condition": {
            "type": "ilikewood:config",
            "config": "beds"
          }
        }
      ]
    }
  ],
  "input": {
    "ingredient": {
      "item": "ilikewood:black_cherry_bed"
    }
  },
  "mainOutput": {
    "count": 3,
    "item": "minecraft:cherry_planks"
  },
  "secondaryChance": 1.0,
  "secondaryOutput": {
    "count": 3,
    "item": "minecraft:black_wool"
  }
}