{
  "parent": "minecraft:recipes/root",
  "rewards": {
    "recipes": [
      "mekanismtools:iron_paxel"
    ]
  },
  "criteria": {
    "has_iron_axe": {
      "trigger": "minecraft:inventory_changed",
      "conditions": {
        "items": [
          {
            "item": "minecraft:iron_axe"
          }
        ]
      }
    },
    "has_iron_pickaxe": {
      "trigger": "minecraft:inventory_changed",
      "conditions": {
        "items": [
          {
            "item": "minecraft:iron_pickaxe"
          }
        ]
      }
    },
    "has_iron_shovel": {
      "trigger": "minecraft:inventory_changed",
      "conditions": {
        "items": [
          {
            "item": "minecraft:iron_shovel"
          }
        ]
      }
    },
    "has_the_recipe": {
      "trigger": "minecraft:recipe_unlocked",
      "conditions": {
        "recipe": "mekanismtools:iron_paxel"
      }
    }
  },
  "requirements": [
    [
      "has_iron_axe",
      "has_iron_pickaxe",
      "has_iron_shovel",
      "has_the_recipe"
    ]
  ]
}